sapiens_file_interpreter/__init__.py
sapiens_file_interpreter/sapiens_file_interpreter.py
sapiens_file_interpreter-2.0.5.dist-info/LICENSE.txt
sapiens_file_interpreter-2.0.5.dist-info/METADATA
sapiens_file_interpreter-2.0.5.dist-info/WHEEL
sapiens_file_interpreter-2.0.5.dist-info/top_level.txt
sapiens_file_interpreter-2.0.5.dist-info/RECORD
