Metadata-Version: 2.2
Name: sapiens_file_interpreter
Version: 2.0.5
Home-page: https://github.com/sapiens-technology/sapiens_file_interpreter
Author: SAPIENS TECHNOLOGY
License: Proprietary Software
License-File: LICENSE.txt
Requires-Dist: paddleocr==2.7.3
Requires-Dist: paddlepaddle==2.6.1
Requires-Dist: moviepy==1.0.3
Requires-Dist: INFINITE-CONTEXT-WINDOW
Dynamic: author
Dynamic: home-page
Dynamic: license
Dynamic: requires-dist
